pysourcegen/__init__.py
pysourcegen/cgen/__init__.py
pysourcegen/cgen/body.py
pysourcegen/cgen/comment.py
pysourcegen/cgen/enum.py
pysourcegen/cgen/file.py
pysourcegen/cgen/function.py
pysourcegen/cgen/header.py
pysourcegen/cgen/item.py
pysourcegen/cgen/switch.py
pysourcegen/cgen/text.py
pysourcegen/cgen/variable.py
pysourcegen/cppgen/__init__.py
pysourcegen/cppgen/body.py
pysourcegen/cppgen/cclass.py
pysourcegen/cppgen/comment.py
pysourcegen/cppgen/enum.py
pysourcegen/cppgen/file.py
pysourcegen/cppgen/function.py
pysourcegen/cppgen/header.py
pysourcegen/cppgen/item.py
pysourcegen/cppgen/namespace.py
pysourcegen/cppgen/switch.py
pysourcegen/cppgen/text.py
pysourcegen/cppgen/variable.py
pysourcegen-0.0.3.dist-info/METADATA
pysourcegen-0.0.3.dist-info/WHEEL
pysourcegen-0.0.3.dist-info/licenses/LICENSE
pysourcegen-0.0.3.dist-info/RECORD
