Metadata-Version: 2.4
Name: pysourcegen
Version: 0.0.3
Summary: Python Source Code Generator
Project-URL: Homepage, https://github.com/Compen/pysourcegen
Project-URL: Issues, https://github.com/Compen/pysourcegen/issues
Author-email: Pieter Compen <info@compen.net>
License-File: LICENSE
Classifier: Operating System :: OS Independent
Classifier: Programming Language :: Python :: 3
Requires-Python: >=3.8
